jareutil/__init__.py
jareutil/evaluation_result.py
jareutil/load_input.py
jareutil/save_output.py
jareutil/solution_for_xml.py
jareutil-0.0.1.dist-info/LICENSE
jareutil-0.0.1.dist-info/METADATA
jareutil-0.0.1.dist-info/WHEEL
jareutil-0.0.1.dist-info/top_level.txt
jareutil-0.0.1.dist-info/RECORD
