Metadata-Version: 2.1
Name: jareutil
Version: 0.0.1
Summary: Load input and save output in Jare evaluator
Home-page: http://147.91.204.116:8888/lazar.krstic/jareutil-python
Author: Lazar Krstic
Author-email: lazarkrstic94@gmail.com
License: UNKNOWN
Platform: UNKNOWN
Classifier: Programming Language :: Python :: 3
Classifier: License :: OSI Approved :: MIT License
Classifier: Operating System :: OS Independent
Requires-Python: >=3.6
